atxp/__init__.py
atxp-0.0.0.dist-info/METADATA
atxp-0.0.0.dist-info/WHEEL
atxp-0.0.0.dist-info/top_level.txt
atxp-0.0.0.dist-info/RECORD
