Metadata-Version: 2.4
Name: atxp
Version: 0.0.0
Summary: Coming soon
Author-email: David Noël-Romas <dnr@novellum.ai>
